LICENSE.txt
MANIFEST.in
setup.py
vaex/ui/__init__.py
vaex/ui/_version.py
vaex/ui/attic.py
vaex/ui/colormaps.py
vaex/ui/columns.py
vaex/ui/completer.py
vaex/ui/expressions.py
vaex/ui/gbin.py
vaex/ui/imageblending.py
vaex/ui/layers.py
vaex/ui/main.py
vaex/ui/plot_windows.py
vaex/ui/qt.py
vaex/ui/ranking.py
vaex/ui/rthook_pyqt4.py
vaex/ui/storage.py
vaex/ui/table.py
vaex/ui/template_matplotlib.py
vaex/ui/templates.py
vaex/ui/undo.py
vaex/ui/user.py
vaex/ui/variables.py
vaex/ui/volumerendering.py
vaex/ui/widgets.py
vaex/ui/icons/__init__.py
vaex/ui/icons/application_link.png
vaex/ui/icons/arrow-circle-double-135.png
vaex/ui/icons/arrow-curve-000-left.png
vaex/ui/icons/arrow-curve-180-left.png
vaex/ui/icons/arrow_out.png
vaex/ui/icons/block--arrow.png
vaex/ui/icons/chart_bar.png
vaex/ui/icons/contrast.png
vaex/ui/icons/control-stop-square.png
vaex/ui/icons/cross-small.png
vaex/ui/icons/cross.png
vaex/ui/icons/cursor.png
vaex/ui/icons/cutlery-knife.png
vaex/ui/icons/database-cloud.png
vaex/ui/icons/dialog-cancel-3.png
vaex/ui/icons/direction.png
vaex/ui/icons/drive-globe.png
vaex/ui/icons/drive.png
vaex/ui/icons/edit-mathematics.png
vaex/ui/icons/edit-move.png
vaex/ui/icons/funnel--arrow.png
vaex/ui/icons/gear.png
vaex/ui/icons/glue_and.png
vaex/ui/icons/glue_and16.png
vaex/ui/icons/glue_cross.png
vaex/ui/icons/glue_lasso.png
vaex/ui/icons/glue_lasso16.png
vaex/ui/icons/glue_move.png
vaex/ui/icons/glue_or.png
vaex/ui/icons/glue_or16.png
vaex/ui/icons/glue_replace.png
vaex/ui/icons/glue_replace16.png
vaex/ui/icons/glue_spectrum.png
vaex/ui/icons/glue_square.png
vaex/ui/icons/glue_square16.png
vaex/ui/icons/glue_xrange_select.png
vaex/ui/icons/glue_xrange_select16.png
vaex/ui/icons/glue_yrange_select.png
vaex/ui/icons/glue_yrange_select16.png
vaex/ui/icons/glue_zoom_to_rect.png
vaex/ui/icons/house.png
vaex/ui/icons/image-export.png
vaex/ui/icons/lasso.png
vaex/ui/icons/lasso16.png
vaex/ui/icons/layer--arrange-back.png
vaex/ui/icons/layer--arrange.png
vaex_ui.egg-info/PKG-INFO
vaex_ui.egg-info/SOURCES.txt
vaex_ui.egg-info/dependency_links.txt
vaex_ui.egg-info/not-zip-safe
vaex_ui.egg-info/requires.txt
vaex_ui.egg-info/top_level.txt