Metadata-Version: 1.0
Name: vaex-ui
Version: 0.2.2
Summary: Graphical user interface for vaex based on Qt
Home-page: https://www.github.com/maartenbreddels/vaex
Author: Maarten A. Breddels
Author-email: maartenbreddels@gmail.com
License: MIT
Platform: UNKNOWN
